think_sql/__init__.py
think_sql/dm/__init__.py
think_sql/dm/db.py
think_sql/dm/table.py
think_sql/dm/util.py
think_sql/mysql/__init__.py
think_sql/mysql/db.py
think_sql/mysql/parse.py
think_sql/mysql/sql_helper.py
think_sql/mysql/table.py
think_sql/mysql/util.py
think_sql/tool/__init__.py
think_sql/tool/base.py
think_sql/tool/cache.py
think_sql/tool/interface.py
think_sql/tool/util.py
think_sql-0.7.8.dist-info/WHEEL
think_sql-0.7.8.dist-info/METADATA
think_sql-0.7.8.dist-info/RECORD
