Metadata-Version: 2.1
Name: think-sql
Version: 0.7.8
Summary: ThinkSQL link think-orm(ThinkPHP)
Home-page: https://github.com/hbh112233abc/think-sql
License: MIT
Keywords: sql,think-sql,DB,Table,mysql,达梦
Author: hbh112233abc
Author-email: hbh112233abc@163.com
Requires-Python: >=3.8,<4.0
Classifier: License :: OSI Approved :: MIT License
Classifier: Programming Language :: Python :: 3
Classifier: Programming Language :: Python :: 3.10
Classifier: Programming Language :: Python :: 3.8
Classifier: Programming Language :: Python :: 3.9
Provides-Extra: all
Provides-Extra: dm
Provides-Extra: mysql
Requires-Dist: cacheout (>=0.15.0,<0.16.0)
Requires-Dist: dill (>=0.3.7,<0.4.0)
Requires-Dist: dmpython (>=2.5.5,<3.0.0); extra == "dm" or extra == "all"
Requires-Dist: jsonpath (>=0.82.2,<0.83.0)
Requires-Dist: loguru (>=0.7.2,<0.8.0)
Requires-Dist: pydantic (>=2.5.2,<3.0.0)
Requires-Dist: pymysql (>=1.1.0,<2.0.0); extra == "mysql" or extra == "all"
Requires-Dist: redis (>=5.0.3,<6.0.0)
Requires-Dist: sql-metadata (>=2.10.0,<3.0.0); extra == "mysql" or extra == "all"
Requires-Dist: sqlparse (>=0.4.4,<0.5.0); extra == "mysql" or extra == "all"
Requires-Dist: tabulate (>=0.9.0,<0.10.0); extra == "mysql" or extra == "all"
Project-URL: Documentation, https://github.com/hbh112233abc/think-sql
Project-URL: Repository, https://github.com/hbh112233abc/think-sql
